pyqt_line_number_widget/__init__.py
pyqt_line_number_widget/lineNumberWidget.py
pyqt_line_number_widget-0.0.1.dist-info/LICENSE
pyqt_line_number_widget-0.0.1.dist-info/METADATA
pyqt_line_number_widget-0.0.1.dist-info/WHEEL
pyqt_line_number_widget-0.0.1.dist-info/top_level.txt
pyqt_line_number_widget-0.0.1.dist-info/RECORD
