Metadata-Version: 2.1
Name: pyqt-line-number-widget
Version: 0.0.1
Summary: QWidget which shows line numbers of QTextBrowser or QTextEdit
Home-page: https://github.com/yjg30737/pyqt-line-number-widget.git
Author: Jung Gyu Yoon
Author-email: yjg30737@gmail.com
License: MIT
Platform: UNKNOWN
License-File: LICENSE
Requires-Dist: PyQt5 (>=5.8)
